{ "compressionlevel":-1,
 "height":11,
 "infinite":false,
 "layers":[
        {
         "data":[0, 0, 0, 0, 0, 0, 0, 0, 0, 0, 0, 0, 0, 0, 0, 0, 0, 0, 0, 0,
            0, 3909, 3910, 3910, 3910, 3910, 3910, 3910, 3910, 3910, 3910, 3910, 3910, 3910, 3910, 3910, 3910, 3910, 3911, 0,
            0, 4022, 585, 585, 585, 585, 585, 585, 585, 585, 585, 585, 585, 585, 585, 585, 585, 585, 4024, 0,
            0, 4022, 585, 585, 585, 585, 585, 585, 585, 585, 585, 585, 585, 585, 585, 585, 585, 585, 1073746073, 0,
            0, 4022, 585, 585, 585, 585, 585, 585, 585, 585, 585, 585, 585, 585, 585, 585, 585, 585, 4023, 4594,
            0, 4022, 585, 585, 585, 585, 585, 585, 585, 585, 585, 585, 585, 585, 585, 585, 585, 585, 4023, 4594,
            0, 4022, 585, 585, 585, 585, 585, 585, 585, 585, 585, 585, 585, 838, 585, 585, 585, 585, 4023, 4594,
            0, 4022, 585, 585, 585, 585, 585, 585, 585, 585, 585, 585, 585, 838, 585, 585, 585, 585, 4249, 0,
            0, 4022, 585, 585, 585, 585, 585, 585, 585, 585, 585, 585, 585, 585, 585, 585, 585, 585, 4024, 0,
            0, 4022, 585, 585, 585, 585, 585, 585, 585, 585, 585, 585, 585, 585, 585, 585, 585, 585, 4024, 0,
            0, 0, 0, 0, 0, 0, 0, 0, 0, 0, 0, 0, 0, 0, 0, 0, 0, 0, 0, 0],
         "height":11,
         "id":1,
         "name":"Floors",
         "opacity":1,
         "type":"tilelayer",
         "visible":true,
         "width":20,
         "x":0,
         "y":0
        }, 
        {
         "data":[1871, 4140, 4366, 4140, 4140, 4366, 4140, 4140, 4366, 4140, 4140, 4366, 4140, 4140, 4366, 4140, 4140, 4366, 4140, 4146,
            2436, 0, 0, 5141, 0, 0, 0, 0, 0, 4689, 0, 0, 0, 0, 0, 0, 0, 0, 0, 4026,
            2436, 0, 0, 5254, 4483, 0, 4488, 4489, 0, 4802, 0, 0, 4598, 0, 0, 0, 0, 4595, 0, 4026,
            2436, 0, 0, 0, 0, 0, 4601, 4602, 0, 0, 0, 0, 0, 0, 0, 0, 0, 0, 0, 4139,
            2436, 0, 0, 0, 0, 4115, 4116, 4117, 4596, 0, 0, 0, 0, 0, 0, 0, 0, 4948, 0, 0,
            2436, 0, 0, 0, 0, 4228, 3436, 4230, 0, 0, 0, 0, 0, 0, 0, 0, 0, 0, 0, 0,
            2436, 0, 0, 0, 0, 4341, 4342, 4343, 0, 0, 0, 4486, 4487, 0, 0, 0, 0, 4948, 0, 0,
            2436, 0, 4481, 4915, 0, 0, 0, 0, 0, 2147489007, 0, 4599, 4600, 0, 0, 0, 0, 0, 0, 3913,
            2436, 0, 0, 5028, 0, 4597, 0, 0, 0, 2147489120, 0, 0, 0, 0, 4595, 0, 4481, 0, 0, 4026,
            2436, 0, 0, 0, 0, 0, 0, 0, 0, 0, 0, 0, 4484, 0, 0, 0, 0, 0, 0, 4026,
            4031, 3914, 3914, 3914, 3914, 3914, 3914, 3914, 3914, 3914, 3914, 3914, 3914, 3914, 3914, 3914, 3914, 3914, 3914, 4030],
         "height":11,
         "id":2,
         "name":"Decorations",
         "opacity":1,
         "type":"tilelayer",
         "visible":true,
         "width":20,
         "x":0,
         "y":0
        }, 
        {
         "data":[1, 1, 1, 1, 1, 1, 1, 1, 1, 1, 1, 1, 1, 1, 1, 1, 1, 1, 1, 1,
            1, 0, 0, 1, 0, 0, 0, 0, 0, 1, 0, 0, 0, 0, 0, 0, 0, 0, 0, 1,
            1, 0, 0, 1, 0, 0, 0, 0, 0, 1, 0, 0, 0, 0, 0, 1, 0, 0, 0, 1,
            1, 0, 0, 0, 0, 0, 0, 0, 0, 0, 0, 0, 0, 0, 0, 0, 0, 0, 0, 1,
            1, 0, 0, 0, 0, 0, 0, 0, 0, 0, 0, 0, 0, 0, 0, 0, 0, 0, 0, 0,
            1, 0, 0, 0, 0, 0, 0, 0, 0, 0, 0, 0, 0, 0, 0, 0, 0, 0, 0, 0,
            1, 0, 0, 0, 0, 0, 0, 0, 0, 0, 0, 0, 0, 0, 0, 0, 0, 0, 0, 0,
            1, 0, 0, 1, 0, 0, 0, 0, 0, 1, 0, 0, 0, 0, 0, 0, 0, 0, 0, 1,
            1, 0, 0, 1, 0, 0, 0, 0, 0, 1, 0, 0, 0, 0, 0, 0, 0, 0, 0, 1,
            1, 0, 0, 0, 0, 0, 0, 0, 0, 0, 0, 0, 0, 0, 0, 0, 0, 0, 0, 1,
            1, 1, 1, 1, 1, 1, 1, 1, 1, 1, 1, 1, 1, 1, 1, 1, 1, 1, 1, 1],
         "height":11,
         "id":3,
         "name":"Walls",
         "opacity":1,
         "type":"tilelayer",
         "visible":true,
         "width":20,
         "x":0,
         "y":0
        },
        {
         "data":[0, 0, 6876, 0, 0, 6876, 0, 0, 6876, 0, 0, 6876, 0, 0, 6876, 0, 0, 6876, 0, 0,
            0, 0, 0, 0, 0, 0, 0, 0, 0, 0, 0, 0, 0, 0, 0, 0, 0, 0, 0, 0,
            0, 0, 0, 0, 0, 0, 0, 0, 0, 0, 0, 0, 0, 0, 0, 4170, 0, 0, 0, 0,
            0, 0, 0, 0, 0, 0, 0, 0, 0, 0, 0, 0, 0, 0, 0, 0, 0, 0, 0, 0,
            0, 0, 0, 0, 0, 0, 0, 0, 0, 0, 0, 0, 0, 0, 0, 0, 0, 0, 0, 0,
            0, 0, 0, 0, 0, 0, 0, 0, 0, 0, 0, 0, 0, 0, 0, 0, 0, 0, 0, 0,
            0, 0, 0, 0, 0, 0, 0, 0, 0, 0, 0, 0, 0, 0, 0, 0, 0, 0, 0, 0,
            0, 0, 0, 0, 0, 0, 0, 0, 0, 0, 0, 0, 0, 0, 0, 0, 0, 0, 0, 0,
            0, 0, 0, 0, 0, 0, 0, 0, 0, 0, 0, 0, 0, 0, 0, 0, 0, 0, 0, 0,
            0, 0, 0, 0, 0, 0, 0, 0, 0, 0, 0, 0, 0, 0, 0, 0, 0, 0, 0, 0,
            0, 0, 0, 0, 0, 0, 0, 0, 0, 0, 0, 0, 0, 0, 0, 0, 0, 0, 0, 0],
         "height":11,
         "id":4,
         "name":"Objects",
         "opacity":1,
         "type":"tilelayer",
         "visible":true,
         "width":20,
         "x":0,
         "y":0
        }],
 "nextlayerid":8,
 "nextobjectid":5,
 "orientation":"orthogonal",
 "renderorder":"right-down",
 "tiledversion":"1.11.2",
 "tileheight":16,
 "tilesets":[
        {
         "columns":113,
         "firstgid":1,
         "image":"..\/assets\/Dungeon.png",
         "imageheight":1212,
         "imagewidth":1808,
         "margin":0,
         "name":"Dungeon",
         "spacing":0,
         "tilecount":8475,
         "tileheight":16,
         "tilewidth":16
        }],
 "tilewidth":16,
 "type":"map",
 "version":"1.10",
 "width":20
}